pyramm/__init__.py
pyramm/api.py
pyramm/cache.py
pyramm/config.py
pyramm/constants.py
pyramm/db.py
pyramm/geometry.py
pyramm/helpers.py
pyramm/logging.py
pyramm/ops/__init__.py
pyramm/ops/top_surface.py
pyramm/tables.py
pyramm/version.py
pyramm-1.43.dist-info/LICENSE
pyramm-1.43.dist-info/METADATA
pyramm-1.43.dist-info/WHEEL
pyramm-1.43.dist-info/RECORD
