Metadata-Version: 2.3
Name: pyramm
Version: 1.43
Summary: Provides a wrapper to the RAMM API and additional tools for positional referencing
License: MIT
Keywords: CAPTIF,RAMM
Author: John Bull
Requires-Python: >=3.10,<4.0
Classifier: License :: OSI Approved :: MIT License
Classifier: Programming Language :: Python :: 3
Classifier: Programming Language :: Python :: 3.10
Classifier: Programming Language :: Python :: 3.11
Classifier: Programming Language :: Python :: 3.12
Classifier: Programming Language :: Python :: 3.13
Requires-Dist: frozendict (>=2.4.6,<3.0.0)
Requires-Dist: geopandas (>=1.0.1,<2.0.0)
Requires-Dist: numpy (>=2.0,<3.0)
Requires-Dist: pandas (>=2.2,<3.0)
Requires-Dist: pyproj (>=3.7.0,<4.0.0)
Requires-Dist: requests (>=2.32.3,<3.0.0)
Requires-Dist: scipy (>=1.14.1,<2.0.0)
Requires-Dist: shapely (>=2.0.6,<3.0.0)
Requires-Dist: sqlalchemy (>=2.0.36,<3.0.0)
Requires-Dist: unsync (>=1.4.0,<2.0.0)
Project-URL: Homepage, https://github.com/captif-nz/pyramm
